__init__.py
generate.py
fakeratata-1.0.0.dist-info/LICENSE
fakeratata-1.0.0.dist-info/METADATA
fakeratata-1.0.0.dist-info/WHEEL
fakeratata-1.0.0.dist-info/top_level.txt
fakeratata-1.0.0.dist-info/RECORD
