Metadata-Version: 2.1
Name: fakeratata
Version: 1.0.0
Summary: Generates fake names
Author-email: Atani Oyinbunua <oyinbunuaatani@gmail.com>
Project-URL: Homepage, https://github.com/karazo/fakename
Keywords: name,generator,tutorial
Classifier: License :: OSI Approved :: MIT License
Classifier: Programming Language :: Python
Classifier: Programming Language :: Python :: 3
Requires-Python: >=3.9
License-File: LICENSE
